<?xml version="1.0" encoding="utf-8" ?>
<dwsync>
<file name="Image1.png" server="C:/xampp/htdocs/VA/" local="132393811847249888" remote="132393811840000000" Dst="2" />
<file name="Image2.png" server="C:/xampp/htdocs/VA/" local="132393815860654904" remote="132393815860000000" Dst="2" />
<file name="Image3.png" server="C:/xampp/htdocs/VA/" local="132393816727371135" remote="132393816720000000" Dst="2" />
<file name="logo.png" server="C:/xampp/htdocs/VA/" local="132395486017508553" remote="132395486010000000" Dst="2" />
<file name="team1.png" server="C:/xampp/htdocs/VA/" local="132393802748960387" remote="132393802740000000" Dst="2" />
<file name="team5.png" server="C:/xampp/htdocs/VA/" local="132393803926637120" remote="132393803920000000" Dst="2" />
<file name="team6.png" server="C:/xampp/htdocs/VA/" local="132393810549004856" remote="132393810540000000" Dst="2" />
<file name="logo.png" server="C:/xampp/htdocs/VA" local="132395486017508553" remote="132395486010000000" Dst="2" />
<file name="team1.png" server="C:/xampp/htdocs/VA" local="132393802748960387" remote="132393802740000000" Dst="2" />
<file name="team5.png" server="C:/xampp/htdocs/VA" local="132393803926637120" remote="132393803920000000" Dst="2" />
<file name="team6.png" server="C:/xampp/htdocs/VA" local="132393810549004856" remote="132393810540000000" Dst="2" />
<file name="Image1.png" server="C:/wamp64/www/VA/" local="132393811847249888" remote="132393811840000000" Dst="2" />
<file name="Image2.png" server="C:/wamp64/www/VA/" local="132393815860654904" remote="132393815860000000" Dst="2" />
<file name="Image3.png" server="C:/wamp64/www/VA/" local="132393816727371135" remote="132393816720000000" Dst="2" />
<file name="logo.png" server="C:/wamp64/www/VA/" local="132395486017508553" remote="132395486010000000" Dst="2" />
<file name="team1.png" server="C:/wamp64/www/VA/" local="132393802748960387" remote="132393802740000000" Dst="2" />
<file name="team5.png" server="C:/wamp64/www/VA/" local="132393803926637120" remote="132393803920000000" Dst="2" />
<file name="team6.png" server="C:/wamp64/www/VA/" local="132393810549004856" remote="132393810540000000" Dst="2" />
<file name="image4.png" server="C:/wamp64/www/VA/" local="132398452026746763" remote="132398452020000000" Dst="2" />
<file name="image5.png" server="C:/wamp64/www/VA/" local="132398452373974976" remote="132398452370000000" Dst="2" />
</dwsync>